matyan/.matyan.ini
matyan/__init__.py
matyan/auto_correct.py
matyan/config.py
matyan/constants.py
matyan/helpers.py
matyan/labels.py
matyan/logger.py
matyan/patterns.py
matyan/registry.py
matyan/utils.py
matyan/fetchers/__init__.py
matyan/fetchers/base.py
matyan/fetchers/jira.py
matyan/renderers/__init__.py
matyan/renderers/base.py
matyan/renderers/markdown.py
matyan/renderers/rest.py
matyan/tests/__init__.py
matyan/tests/base.py
matyan/tests/mixins.py
matyan/tests/test_auto_correct.py
matyan/tests/test_commands.py
matyan/tests/test_core.py
matyan/tests/output/generate-changelog-headings-only.md
matyan/tests/output/generate-changelog-latest-release-show-releases.md
matyan/tests/output/generate-changelog-show-releases-headings-only.md
matyan/tests/output/generate-changelog-show-releases-rend-hist.md
matyan/tests/output/generate-changelog-show-releases-unreleased-only.md
matyan/tests/output/generate-changelog-show-releases.md
matyan/tests/output/generate-changelog-show-releases.rst
matyan/tests/output/generate-changelog.md
matyan/tests/output/json-changelog-headings-only.json
matyan/tests/output/json-changelog-latest-release-show-releases.json
matyan/tests/output/json-changelog-show-releases-headings-only.json
matyan/tests/output/json-changelog-show-releases.json
matyan/tests/output/json-changelog.json
matyan-0.4.7.dist-info/LICENSE_GPL2.0.txt
matyan-0.4.7.dist-info/LICENSE_LGPL_2.1.txt
matyan-0.4.7.dist-info/METADATA
matyan-0.4.7.dist-info/WHEEL
matyan-0.4.7.dist-info/entry_points.txt
matyan-0.4.7.dist-info/top_level.txt
matyan-0.4.7.dist-info/RECORD
