Metadata-Version: 2.1
Name: matyan
Version: 0.4.7
Summary: Generate changelog from Git commits.
Home-page: https://github.com/barseghyanartur/matyan
Author: Artur Barseghyan
Author-email: artur.barseghyan@gmail.com
License: GPL-2.0-only OR LGPL-2.1-or-later
Project-URL: Bug Tracker, https://github.com/barseghyanartur/matyan/issues
Project-URL: Documentation, https://matyan.readthedocs.io/
Project-URL: Source Code, https://github.com/barseghyanartur/matyan/
Project-URL: Changelog, https://matyan.readthedocs.io/en/latest/changelog.html
Keywords: Changelog,logbook,Git,feature branches,gitflow,JIRA,agile
Platform: UNKNOWN
Classifier: Programming Language :: Python
Classifier: Programming Language :: Python :: 3
Classifier: Programming Language :: Python :: 3.6
Classifier: Programming Language :: Python :: 3.7
Classifier: Programming Language :: Python :: 3.8
Classifier: Environment :: Web Environment
Classifier: Intended Audience :: Developers
Classifier: Operating System :: OS Independent
Classifier: Development Status :: 4 - Beta
Classifier: Topic :: Internet
Classifier: License :: OSI Approved :: GNU General Public License v2 (GPLv2)
Classifier: License :: OSI Approved :: GNU Lesser General Public License v2 or later (LGPLv2+)
Requires-Dist: GitPython
Provides-Extra: jira
Requires-Dist: atlassian-python-api ; extra == 'jira'
